zzipdoc/__init__.py
zzipdoc/commentmarkup.py
zzipdoc/dbk2htm.py
zzipdoc/docbookdocument.py
zzipdoc/functionheader.py
zzipdoc/functionlisthtmlpage.py
zzipdoc/functionlistreference.py
zzipdoc/functionprototype.py
zzipdoc/htm2dbk.py
zzipdoc/htmldoctypes.py
zzipdoc/htmldocument.py
zzipdoc/match.py
zzipdoc/py.typed
zzipdoc/textfile.py
zzipdoc/textfileheader.py
zzipdoctool/__init__.py
zzipdoctool/cpp2markdown-1.py
zzipdoctool/cpp2markdown.py
zzipdoctool/dbk2man.py
zzipdoctool/dir2index.py
zzipdoctool/md2dbk.py
zzipdoctool/mdhtm.py
zzipdoctool/py.typed
zzipmakedocs-0.13.80.data/scripts/zzipbuildtests.py
zzipmakedocs-0.13.80.data/scripts/zzipdoctooltests.py
zzipmakedocs-0.13.80.data/scripts/zzipmakedocs.py
zzipmakedocs-0.13.80.data/scripts/zziptests.py
zzipmakedocs-0.13.80.dist-info/licenses/docs/COPYING.ZLIB
zzipmakedocs-0.13.80.dist-info/METADATA
zzipmakedocs-0.13.80.dist-info/WHEEL
zzipmakedocs-0.13.80.dist-info/entry_points.txt
zzipmakedocs-0.13.80.dist-info/top_level.txt
zzipmakedocs-0.13.80.dist-info/RECORD
