Metadata-Version: 2.2
Name: zzipmakedocs
Version: 0.13.80
Summary: generate troff manpages and htm manual pages from C source comments via docbook reference and markdown parts
Author-email: "Guido U. Draheim" <Guido.Draheim@gmx.de>
License-Expression: Zlib
Project-URL: homepage, https://github.com/gdraheim/zziplib
Project-URL: repository, https://github.com/gdraheim/zziplib.git
Project-URL: issues, https://github.com/gdraheim/zziplib/issues
Classifier: Environment :: Console
Classifier: Programming Language :: Python :: 3
Classifier: Topic :: Software Development :: Code Generators
Classifier: Topic :: Text Processing :: Filters
Classifier: Typing :: Typed
License-File: docs/COPYING.ZLIB
Provides-Extra: dev
Requires-Dist: build; extra == "dev"
Dynamic: license-file
